xcookie/__init__.py
xcookie/__main__.py
xcookie/__main__.pyi
xcookie/constants.py
xcookie/directive.py
xcookie/main.py
xcookie/main.pyi
xcookie/py.typed
xcookie/rich_ext.py
xcookie/util_yaml.py
xcookie/vcs_remotes.py
xcookie/builders/__init__.py
xcookie/builders/_builder.py
xcookie/builders/common_ci.py
xcookie/builders/docs.py
xcookie/builders/github_actions.py
xcookie/builders/gitlab_ci.py
xcookie/builders/pyproject.py
xcookie/builders/readme.py
xcookie/builders/readthedocs.py
xcookie/builders/setup.py
xcookie/rc/CMakeLists.txt.in
xcookie/rc/__init__.py
xcookie/rc/conf_ext.py
xcookie/rc/dependabot.yml.in
xcookie/rc/docs_make.bat.in
xcookie/rc/docs_makefile.in
xcookie/rc/gitignore.in
xcookie/rc/gitlab-ci.binpy.yml.in
xcookie/rc/gitlab-ci.purepy.yml.in
xcookie/rc/publish.sh.in
xcookie/rc/run_tests.binpy.py.in
xcookie/rc/run_tests.purepy.py.in
xcookie/rc/setup.py.in
xcookie/rc/setup_secrets.sh.in
xcookie/rc/test_binaries.yml.in
xcookie/rc/tests.yml.in
xcookie/vcs/__init__.py
xcookie/vcs/github.py
xcookie/vcs/gitlab.py
xcookie-0.3.1.dist-info/licenses/LICENSE
xcookie-0.3.1.dist-info/METADATA
xcookie-0.3.1.dist-info/WHEEL
xcookie-0.3.1.dist-info/entry_points.txt
xcookie-0.3.1.dist-info/top_level.txt
xcookie-0.3.1.dist-info/RECORD
