Metadata-Version: 2.4
Name: xcookie
Version: 0.3.1
Summary: The xcookie cookie-cutter Module
Home-page: https://github.com/Erotemic/xcookie
Author: Jon Crall
Author-email: erotemic@gmail.com
License: Apache 2
Classifier: Development Status :: 1 - Planning
Classifier: Intended Audience :: Developers
Classifier: Topic :: Software Development :: Libraries :: Python Modules
Classifier: Topic :: Utilities
Classifier: License :: OSI Approved :: Apache Software License
Classifier: Programming Language :: Python :: 3.7
Classifier: Programming Language :: Python :: 3.8
Classifier: Programming Language :: Python :: 3.9
Classifier: Programming Language :: Python :: 3.10
Classifier: Programming Language :: Python :: 3.11
Classifier: Programming Language :: Python :: 3.12
Classifier: Programming Language :: Python :: 3.13
Requires-Python: >=3.7
License-File: LICENSE
Requires-Dist: xdev>=1.5.3; python_version >= "3.6"
Requires-Dist: ubelt>=1.3.6; python_version >= "3.6"
Requires-Dist: toml>=0.9.6; python_version >= "2.7"
Requires-Dist: scriptconfig>=0.7.10; python_version >= "3.6"
Requires-Dist: rich>=12.3.0
Requires-Dist: git-python>=1.0.0; python_version >= "2.7"
Requires-Dist: black>=22.1.0; python_version >= "3.6.2"
Requires-Dist: packaging>=21.3
Requires-Dist: ruamel.yaml<=0.17.32,>=0.17.22
Requires-Dist: PyYAML>=6.0.2; python_version < "4.0" and python_version >= "3.12"
Requires-Dist: PyYAML>=6.0; python_version < "3.12"
Requires-Dist: argcomplete>=1.0
Requires-Dist: pandas>=2.2.3; python_version < "4.0" and python_version >= "3.13"
Requires-Dist: pandas>=1.5.0; python_version < "3.12" and python_version >= "3.11"
Requires-Dist: pandas>=1.3.5; python_version < "3.11" and python_version >= "3.10"
Requires-Dist: pandas>=1.4.0; python_version < "3.10" and python_version >= "3.9"
Requires-Dist: pandas>=1.4.0; python_version < "3.9" and python_version >= "3.8"
Requires-Dist: pandas>=1.2.0; python_version < "3.8" and python_version >= "3.7"
Requires-Dist: pandas>=1.1.4; python_version < "3.7" and python_version >= "3.6"
Requires-Dist: numpy>=2.1.2; python_version < "4.0" and python_version >= "3.13"
Requires-Dist: numpy>=1.26.0; python_version < "3.13" and python_version >= "3.12"
Requires-Dist: numpy>=1.23.2; python_version < "3.12" and python_version >= "3.11"
Requires-Dist: numpy>=1.21.6; python_version < "3.11" and python_version >= "3.10"
Requires-Dist: numpy>=1.19.3; python_version < "3.10" and python_version >= "3.9"
Requires-Dist: numpy>=1.22.0; sys_platform == "darwin" and python_version < "3.9" and python_version >= "3.8"
Requires-Dist: numpy>=1.20.0; sys_platform != "darwin" and python_version < "3.9" and python_version >= "3.8"
Requires-Dist: numpy>=1.19.3; python_version < "3.8" and python_version >= "3.7"
Requires-Dist: cmd_queue>=0.1.6
Requires-Dist: sphinx>=5.0.1
Requires-Dist: sphinx-autobuild>=2021.3.14
Requires-Dist: sphinx_rtd_theme>=1.0.0
Requires-Dist: sphinxcontrib-napoleon>=0.7
Requires-Dist: sphinx-autoapi>=1.8.4
Requires-Dist: Pygments>=2.12.0
Requires-Dist: myst_parser>=0.18.0
Requires-Dist: sphinx-reredirects>=0.0.1
Requires-Dist: tabulate>=0.9.0
Provides-Extra: all
Requires-Dist: xdev>=1.5.3; python_version >= "3.6" and extra == "all"
Requires-Dist: ubelt>=1.3.6; python_version >= "3.6" and extra == "all"
Requires-Dist: toml>=0.9.6; python_version >= "2.7" and extra == "all"
Requires-Dist: scriptconfig>=0.7.10; python_version >= "3.6" and extra == "all"
Requires-Dist: rich>=12.3.0; extra == "all"
Requires-Dist: git-python>=1.0.0; python_version >= "2.7" and extra == "all"
Requires-Dist: black>=22.1.0; python_version >= "3.6.2" and extra == "all"
Requires-Dist: packaging>=21.3; extra == "all"
Requires-Dist: ruamel.yaml<=0.17.32,>=0.17.22; extra == "all"
Requires-Dist: PyYAML>=6.0.2; (python_version < "4.0" and python_version >= "3.12") and extra == "all"
Requires-Dist: PyYAML>=6.0; python_version < "3.12" and extra == "all"
Requires-Dist: argcomplete>=1.0; extra == "all"
Requires-Dist: pandas>=2.2.3; (python_version < "4.0" and python_version >= "3.13") and extra == "all"
Requires-Dist: pandas>=1.5.0; (python_version < "3.12" and python_version >= "3.11") and extra == "all"
Requires-Dist: pandas>=1.3.5; (python_version < "3.11" and python_version >= "3.10") and extra == "all"
Requires-Dist: pandas>=1.4.0; (python_version < "3.10" and python_version >= "3.9") and extra == "all"
Requires-Dist: pandas>=1.4.0; (python_version < "3.9" and python_version >= "3.8") and extra == "all"
Requires-Dist: pandas>=1.2.0; (python_version < "3.8" and python_version >= "3.7") and extra == "all"
Requires-Dist: pandas>=1.1.4; (python_version < "3.7" and python_version >= "3.6") and extra == "all"
Requires-Dist: numpy>=2.1.2; (python_version < "4.0" and python_version >= "3.13") and extra == "all"
Requires-Dist: numpy>=1.26.0; (python_version < "3.13" and python_version >= "3.12") and extra == "all"
Requires-Dist: numpy>=1.23.2; (python_version < "3.12" and python_version >= "3.11") and extra == "all"
Requires-Dist: numpy>=1.21.6; (python_version < "3.11" and python_version >= "3.10") and extra == "all"
Requires-Dist: numpy>=1.19.3; (python_version < "3.10" and python_version >= "3.9") and extra == "all"
Requires-Dist: numpy>=1.22.0; (sys_platform == "darwin" and python_version < "3.9" and python_version >= "3.8") and extra == "all"
Requires-Dist: numpy>=1.20.0; (sys_platform != "darwin" and python_version < "3.9" and python_version >= "3.8") and extra == "all"
Requires-Dist: numpy>=1.19.3; (python_version < "3.8" and python_version >= "3.7") and extra == "all"
Requires-Dist: cmd_queue>=0.1.6; extra == "all"
Requires-Dist: sphinx>=5.0.1; extra == "all"
Requires-Dist: sphinx-autobuild>=2021.3.14; extra == "all"
Requires-Dist: sphinx_rtd_theme>=1.0.0; extra == "all"
Requires-Dist: sphinxcontrib-napoleon>=0.7; extra == "all"
Requires-Dist: sphinx-autoapi>=1.8.4; extra == "all"
Requires-Dist: Pygments>=2.12.0; extra == "all"
Requires-Dist: myst_parser>=0.18.0; extra == "all"
Requires-Dist: sphinx-reredirects>=0.0.1; extra == "all"
Requires-Dist: tabulate>=0.9.0; extra == "all"
Requires-Dist: xdoctest>=1.1.6; extra == "all"
Requires-Dist: pytest>=6.2.5; python_version >= "3.10.0" and extra == "all"
Requires-Dist: pytest>=6.2.5; (python_version < "3.10.0" and python_version >= "3.7.0") and extra == "all"
Requires-Dist: pytest-cov>=3.0.0; python_version >= "3.6.0" and extra == "all"
Requires-Dist: pytest-cov>=2.9.0; (python_version < "3.6.0" and python_version >= "3.5.0") and extra == "all"
Requires-Dist: pytest-cov>=2.8.1; (python_version < "3.5.0" and python_version >= "3.4.0") and extra == "all"
Requires-Dist: pytest-cov>=2.8.1; (python_version < "2.8.0" and python_version >= "2.7.0") and extra == "all"
Requires-Dist: pytest-timeout>=1.4.2; extra == "all"
Requires-Dist: coverage>=6.1.1; python_version >= "3.10" and extra == "all"
Requires-Dist: coverage>=5.3.1; (python_version < "3.10" and python_version >= "3.9") and extra == "all"
Requires-Dist: coverage>=6.1.1; (python_version < "3.9" and python_version >= "3.8") and extra == "all"
Requires-Dist: coverage>=6.1.1; (python_version < "3.8" and python_version >= "3.7") and extra == "all"
Requires-Dist: coverage>=6.1.1; (python_version < "3.7" and python_version >= "3.6") and extra == "all"
Requires-Dist: coverage>=5.3.1; (python_version < "3.6" and python_version >= "3.5") and extra == "all"
Requires-Dist: coverage>=4.3.4; (python_version < "3.5" and python_version >= "3.4") and extra == "all"
Requires-Dist: coverage>=5.3.1; (python_version < "3.4" and python_version >= "2.7") and extra == "all"
Requires-Dist: coverage>=4.5; (python_version < "2.7" and python_version >= "2.6") and extra == "all"
Requires-Dist: python-gitlab>=3.0; extra == "all"
Requires-Dist: psycopg2-binary>=2.9.5; (python_version < "4.0" and python_version >= "3.11") and extra == "all"
Requires-Dist: psycopg2-binary>=2.9.1; (python_version < "3.11" and python_version >= "3.10") and extra == "all"
Requires-Dist: psycopg2-binary>=2.8.6; (python_version < "3.10" and python_version >= "3.9") and extra == "all"
Requires-Dist: psycopg2-binary>=2.8.4; (python_version < "3.9" and python_version >= "3.8") and extra == "all"
Requires-Dist: psycopg2-binary>=2.7.5; (python_version < "3.8" and python_version >= "3.7") and extra == "all"
Requires-Dist: psycopg2-binary>=2.7.3.2; (python_version < "3.7" and python_version >= "3.6") and extra == "all"
Requires-Dist: sqlalchemy_utils>=0.40.0; extra == "all"
Provides-Extra: runtime
Requires-Dist: xdev>=1.5.3; python_version >= "3.6" and extra == "runtime"
Requires-Dist: ubelt>=1.3.6; python_version >= "3.6" and extra == "runtime"
Requires-Dist: toml>=0.9.6; python_version >= "2.7" and extra == "runtime"
Requires-Dist: scriptconfig>=0.7.10; python_version >= "3.6" and extra == "runtime"
Requires-Dist: rich>=12.3.0; extra == "runtime"
Requires-Dist: git-python>=1.0.0; python_version >= "2.7" and extra == "runtime"
Requires-Dist: black>=22.1.0; python_version >= "3.6.2" and extra == "runtime"
Requires-Dist: packaging>=21.3; extra == "runtime"
Requires-Dist: ruamel.yaml<=0.17.32,>=0.17.22; extra == "runtime"
Requires-Dist: PyYAML>=6.0.2; (python_version < "4.0" and python_version >= "3.12") and extra == "runtime"
Requires-Dist: PyYAML>=6.0; python_version < "3.12" and extra == "runtime"
Requires-Dist: argcomplete>=1.0; extra == "runtime"
Requires-Dist: pandas>=2.2.3; (python_version < "4.0" and python_version >= "3.13") and extra == "runtime"
Requires-Dist: pandas>=1.5.0; (python_version < "3.12" and python_version >= "3.11") and extra == "runtime"
Requires-Dist: pandas>=1.3.5; (python_version < "3.11" and python_version >= "3.10") and extra == "runtime"
Requires-Dist: pandas>=1.4.0; (python_version < "3.10" and python_version >= "3.9") and extra == "runtime"
Requires-Dist: pandas>=1.4.0; (python_version < "3.9" and python_version >= "3.8") and extra == "runtime"
Requires-Dist: pandas>=1.2.0; (python_version < "3.8" and python_version >= "3.7") and extra == "runtime"
Requires-Dist: pandas>=1.1.4; (python_version < "3.7" and python_version >= "3.6") and extra == "runtime"
Requires-Dist: numpy>=2.1.2; (python_version < "4.0" and python_version >= "3.13") and extra == "runtime"
Requires-Dist: numpy>=1.26.0; (python_version < "3.13" and python_version >= "3.12") and extra == "runtime"
Requires-Dist: numpy>=1.23.2; (python_version < "3.12" and python_version >= "3.11") and extra == "runtime"
Requires-Dist: numpy>=1.21.6; (python_version < "3.11" and python_version >= "3.10") and extra == "runtime"
Requires-Dist: numpy>=1.19.3; (python_version < "3.10" and python_version >= "3.9") and extra == "runtime"
Requires-Dist: numpy>=1.22.0; (sys_platform == "darwin" and python_version < "3.9" and python_version >= "3.8") and extra == "runtime"
Requires-Dist: numpy>=1.20.0; (sys_platform != "darwin" and python_version < "3.9" and python_version >= "3.8") and extra == "runtime"
Requires-Dist: numpy>=1.19.3; (python_version < "3.8" and python_version >= "3.7") and extra == "runtime"
Requires-Dist: cmd_queue>=0.1.6; extra == "runtime"
Requires-Dist: sphinx>=5.0.1; extra == "runtime"
Requires-Dist: sphinx-autobuild>=2021.3.14; extra == "runtime"
Requires-Dist: sphinx_rtd_theme>=1.0.0; extra == "runtime"
Requires-Dist: sphinxcontrib-napoleon>=0.7; extra == "runtime"
Requires-Dist: sphinx-autoapi>=1.8.4; extra == "runtime"
Requires-Dist: Pygments>=2.12.0; extra == "runtime"
Requires-Dist: myst_parser>=0.18.0; extra == "runtime"
Requires-Dist: sphinx-reredirects>=0.0.1; extra == "runtime"
Requires-Dist: tabulate>=0.9.0; extra == "runtime"
Provides-Extra: tests
Requires-Dist: xdoctest>=1.1.6; extra == "tests"
Requires-Dist: pytest>=6.2.5; python_version >= "3.10.0" and extra == "tests"
Requires-Dist: pytest>=6.2.5; (python_version < "3.10.0" and python_version >= "3.7.0") and extra == "tests"
Requires-Dist: pytest-cov>=3.0.0; python_version >= "3.6.0" and extra == "tests"
Requires-Dist: pytest-cov>=2.9.0; (python_version < "3.6.0" and python_version >= "3.5.0") and extra == "tests"
Requires-Dist: pytest-cov>=2.8.1; (python_version < "3.5.0" and python_version >= "3.4.0") and extra == "tests"
Requires-Dist: pytest-cov>=2.8.1; (python_version < "2.8.0" and python_version >= "2.7.0") and extra == "tests"
Requires-Dist: pytest-timeout>=1.4.2; extra == "tests"
Requires-Dist: coverage>=6.1.1; python_version >= "3.10" and extra == "tests"
Requires-Dist: coverage>=5.3.1; (python_version < "3.10" and python_version >= "3.9") and extra == "tests"
Requires-Dist: coverage>=6.1.1; (python_version < "3.9" and python_version >= "3.8") and extra == "tests"
Requires-Dist: coverage>=6.1.1; (python_version < "3.8" and python_version >= "3.7") and extra == "tests"
Requires-Dist: coverage>=6.1.1; (python_version < "3.7" and python_version >= "3.6") and extra == "tests"
Requires-Dist: coverage>=5.3.1; (python_version < "3.6" and python_version >= "3.5") and extra == "tests"
Requires-Dist: coverage>=4.3.4; (python_version < "3.5" and python_version >= "3.4") and extra == "tests"
Requires-Dist: coverage>=5.3.1; (python_version < "3.4" and python_version >= "2.7") and extra == "tests"
Requires-Dist: coverage>=4.5; (python_version < "2.7" and python_version >= "2.6") and extra == "tests"
Provides-Extra: optional
Requires-Dist: python-gitlab>=3.0; extra == "optional"
Provides-Extra: docs
Requires-Dist: sphinx>=5.0.1; extra == "docs"
Requires-Dist: sphinx-autobuild>=2021.3.14; extra == "docs"
Requires-Dist: sphinx_rtd_theme>=1.0.0; extra == "docs"
Requires-Dist: sphinxcontrib-napoleon>=0.7; extra == "docs"
Requires-Dist: sphinx-autoapi>=1.8.4; extra == "docs"
Requires-Dist: Pygments>=2.9.0; extra == "docs"
Requires-Dist: myst_parser>=0.18.0; extra == "docs"
Requires-Dist: sphinx-reredirects>=0.0.1; extra == "docs"
Requires-Dist: docutils>=0.20.1; extra == "docs"
Provides-Extra: gdal-strict
Requires-Dist: GDAL==3.7.2; (python_version < "4.0" and python_version >= "3.12") and extra == "gdal-strict"
Requires-Dist: GDAL==3.5.2; (python_version < "3.12" and python_version >= "3.11") and extra == "gdal-strict"
Requires-Dist: GDAL==3.4.1; (python_version < "3.11" and python_version >= "3.10") and extra == "gdal-strict"
Requires-Dist: GDAL==3.4.1; python_version <= "3.9" and extra == "gdal-strict"
Provides-Extra: gdal
Requires-Dist: GDAL>=3.7.2; (python_version < "4.0" and python_version >= "3.12") and extra == "gdal"
Requires-Dist: GDAL>=3.5.2; (python_version < "3.12" and python_version >= "3.11") and extra == "gdal"
Requires-Dist: GDAL>=3.4.1; (python_version < "3.11" and python_version >= "3.10") and extra == "gdal"
Requires-Dist: GDAL>=3.4.1; python_version <= "3.9" and extra == "gdal"
Provides-Extra: graphics
Requires-Dist: opencv-python>=4.5.5.64; (python_version < "4.0" and python_version >= "3.11") and extra == "graphics"
Requires-Dist: opencv-python>=4.5.4.58; (python_version < "3.11" and python_version >= "3.10") and extra == "graphics"
Requires-Dist: opencv-python>=3.4.15.55; (python_version < "3.10" and python_version >= "3.9") and extra == "graphics"
Requires-Dist: opencv-python>=3.4.15.55; (python_version < "3.9" and python_version >= "3.8") and extra == "graphics"
Requires-Dist: opencv-python>=3.4.15.55; (python_version < "3.8" and python_version >= "3.7") and extra == "graphics"
Requires-Dist: opencv-python>=3.4.13.47; (python_version < "3.7" and python_version >= "3.6") and extra == "graphics"
Requires-Dist: opencv-python>=3.1.0.2; (python_version < "3.6" and python_version >= "3.5") and extra == "graphics"
Requires-Dist: opencv-python>=3.1.0.5; (python_version < "3.5" and python_version >= "3.4") and extra == "graphics"
Requires-Dist: opencv-python>=3.1.0.0; (python_version < "3.4" and python_version >= "2.7") and extra == "graphics"
Provides-Extra: headless
Requires-Dist: opencv-python-headless>=4.5.5.64; (python_version < "4.0" and python_version >= "3.11") and extra == "headless"
Requires-Dist: opencv-python-headless>=4.5.4.58; (python_version < "3.11" and python_version >= "3.10") and extra == "headless"
Requires-Dist: opencv-python-headless>=3.4.15.55; (python_version < "3.10" and python_version >= "3.9") and extra == "headless"
Requires-Dist: opencv-python-headless>=3.4.15.55; (python_version < "3.9" and python_version >= "3.8") and extra == "headless"
Requires-Dist: opencv-python-headless>=3.4.15.55; (python_version < "3.8" and python_version >= "3.7") and extra == "headless"
Requires-Dist: opencv-python-headless>=3.4.13.47; (python_version < "3.7" and python_version >= "3.6") and extra == "headless"
Requires-Dist: opencv-python-headless>=3.4.2.16; (python_version < "3.6" and python_version >= "3.5") and extra == "headless"
Requires-Dist: opencv-python-headless>=3.4.2.16; (python_version < "3.5" and python_version >= "3.4") and extra == "headless"
Requires-Dist: opencv-python-headless>=3.4.2.16; (python_version < "3.4" and python_version >= "2.7") and extra == "headless"
Provides-Extra: postgresql
Requires-Dist: psycopg2-binary>=2.9.5; (python_version < "4.0" and python_version >= "3.11") and extra == "postgresql"
Requires-Dist: psycopg2-binary>=2.9.1; (python_version < "3.11" and python_version >= "3.10") and extra == "postgresql"
Requires-Dist: psycopg2-binary>=2.8.6; (python_version < "3.10" and python_version >= "3.9") and extra == "postgresql"
Requires-Dist: psycopg2-binary>=2.8.4; (python_version < "3.9" and python_version >= "3.8") and extra == "postgresql"
Requires-Dist: psycopg2-binary>=2.7.5; (python_version < "3.8" and python_version >= "3.7") and extra == "postgresql"
Requires-Dist: psycopg2-binary>=2.7.3.2; (python_version < "3.7" and python_version >= "3.6") and extra == "postgresql"
Requires-Dist: sqlalchemy_utils>=0.40.0; extra == "postgresql"
Provides-Extra: all-strict
Requires-Dist: xdev==1.5.3; python_version >= "3.6" and extra == "all-strict"
Requires-Dist: ubelt==1.3.6; python_version >= "3.6" and extra == "all-strict"
Requires-Dist: toml==0.9.6; python_version >= "2.7" and extra == "all-strict"
Requires-Dist: scriptconfig==0.7.10; python_version >= "3.6" and extra == "all-strict"
Requires-Dist: rich==12.3.0; extra == "all-strict"
Requires-Dist: git-python==1.0.0; python_version >= "2.7" and extra == "all-strict"
Requires-Dist: black==22.1.0; python_version >= "3.6.2" and extra == "all-strict"
Requires-Dist: packaging==21.3; extra == "all-strict"
Requires-Dist: ruamel.yaml<=0.17.32,==0.17.22; extra == "all-strict"
Requires-Dist: PyYAML==6.0.2; (python_version < "4.0" and python_version >= "3.12") and extra == "all-strict"
Requires-Dist: PyYAML==6.0; python_version < "3.12" and extra == "all-strict"
Requires-Dist: argcomplete==1.0; extra == "all-strict"
Requires-Dist: pandas==2.2.3; (python_version < "4.0" and python_version >= "3.13") and extra == "all-strict"
Requires-Dist: pandas==1.5.0; (python_version < "3.12" and python_version >= "3.11") and extra == "all-strict"
Requires-Dist: pandas==1.3.5; (python_version < "3.11" and python_version >= "3.10") and extra == "all-strict"
Requires-Dist: pandas==1.4.0; (python_version < "3.10" and python_version >= "3.9") and extra == "all-strict"
Requires-Dist: pandas==1.4.0; (python_version < "3.9" and python_version >= "3.8") and extra == "all-strict"
Requires-Dist: pandas==1.2.0; (python_version < "3.8" and python_version >= "3.7") and extra == "all-strict"
Requires-Dist: pandas==1.1.4; (python_version < "3.7" and python_version >= "3.6") and extra == "all-strict"
Requires-Dist: numpy==2.1.2; (python_version < "4.0" and python_version >= "3.13") and extra == "all-strict"
Requires-Dist: numpy==1.26.0; (python_version < "3.13" and python_version >= "3.12") and extra == "all-strict"
Requires-Dist: numpy==1.23.2; (python_version < "3.12" and python_version >= "3.11") and extra == "all-strict"
Requires-Dist: numpy==1.21.6; (python_version < "3.11" and python_version >= "3.10") and extra == "all-strict"
Requires-Dist: numpy==1.19.3; (python_version < "3.10" and python_version >= "3.9") and extra == "all-strict"
Requires-Dist: numpy==1.22.0; (sys_platform == "darwin" and python_version < "3.9" and python_version >= "3.8") and extra == "all-strict"
Requires-Dist: numpy==1.20.0; (sys_platform != "darwin" and python_version < "3.9" and python_version >= "3.8") and extra == "all-strict"
Requires-Dist: numpy==1.19.3; (python_version < "3.8" and python_version >= "3.7") and extra == "all-strict"
Requires-Dist: cmd_queue==0.1.6; extra == "all-strict"
Requires-Dist: sphinx==5.0.1; extra == "all-strict"
Requires-Dist: sphinx-autobuild==2021.3.14; extra == "all-strict"
Requires-Dist: sphinx_rtd_theme==1.0.0; extra == "all-strict"
Requires-Dist: sphinxcontrib-napoleon==0.7; extra == "all-strict"
Requires-Dist: sphinx-autoapi==1.8.4; extra == "all-strict"
Requires-Dist: Pygments==2.12.0; extra == "all-strict"
Requires-Dist: myst_parser==0.18.0; extra == "all-strict"
Requires-Dist: sphinx-reredirects==0.0.1; extra == "all-strict"
Requires-Dist: tabulate==0.9.0; extra == "all-strict"
Requires-Dist: xdoctest==1.1.6; extra == "all-strict"
Requires-Dist: pytest==6.2.5; python_version >= "3.10.0" and extra == "all-strict"
Requires-Dist: pytest==6.2.5; (python_version < "3.10.0" and python_version >= "3.7.0") and extra == "all-strict"
Requires-Dist: pytest-cov==3.0.0; python_version >= "3.6.0" and extra == "all-strict"
Requires-Dist: pytest-cov==2.9.0; (python_version < "3.6.0" and python_version >= "3.5.0") and extra == "all-strict"
Requires-Dist: pytest-cov==2.8.1; (python_version < "3.5.0" and python_version >= "3.4.0") and extra == "all-strict"
Requires-Dist: pytest-cov==2.8.1; (python_version < "2.8.0" and python_version >= "2.7.0") and extra == "all-strict"
Requires-Dist: pytest-timeout==1.4.2; extra == "all-strict"
Requires-Dist: coverage==6.1.1; python_version >= "3.10" and extra == "all-strict"
Requires-Dist: coverage==5.3.1; (python_version < "3.10" and python_version >= "3.9") and extra == "all-strict"
Requires-Dist: coverage==6.1.1; (python_version < "3.9" and python_version >= "3.8") and extra == "all-strict"
Requires-Dist: coverage==6.1.1; (python_version < "3.8" and python_version >= "3.7") and extra == "all-strict"
Requires-Dist: coverage==6.1.1; (python_version < "3.7" and python_version >= "3.6") and extra == "all-strict"
Requires-Dist: coverage==5.3.1; (python_version < "3.6" and python_version >= "3.5") and extra == "all-strict"
Requires-Dist: coverage==4.3.4; (python_version < "3.5" and python_version >= "3.4") and extra == "all-strict"
Requires-Dist: coverage==5.3.1; (python_version < "3.4" and python_version >= "2.7") and extra == "all-strict"
Requires-Dist: coverage==4.5; (python_version < "2.7" and python_version >= "2.6") and extra == "all-strict"
Requires-Dist: python-gitlab==3.0; extra == "all-strict"
Requires-Dist: psycopg2-binary==2.9.5; (python_version < "4.0" and python_version >= "3.11") and extra == "all-strict"
Requires-Dist: psycopg2-binary==2.9.1; (python_version < "3.11" and python_version >= "3.10") and extra == "all-strict"
Requires-Dist: psycopg2-binary==2.8.6; (python_version < "3.10" and python_version >= "3.9") and extra == "all-strict"
Requires-Dist: psycopg2-binary==2.8.4; (python_version < "3.9" and python_version >= "3.8") and extra == "all-strict"
Requires-Dist: psycopg2-binary==2.7.5; (python_version < "3.8" and python_version >= "3.7") and extra == "all-strict"
Requires-Dist: psycopg2-binary==2.7.3.2; (python_version < "3.7" and python_version >= "3.6") and extra == "all-strict"
Requires-Dist: sqlalchemy_utils==0.40.0; extra == "all-strict"
Provides-Extra: runtime-strict
Requires-Dist: xdev==1.5.3; python_version >= "3.6" and extra == "runtime-strict"
Requires-Dist: ubelt==1.3.6; python_version >= "3.6" and extra == "runtime-strict"
Requires-Dist: toml==0.9.6; python_version >= "2.7" and extra == "runtime-strict"
Requires-Dist: scriptconfig==0.7.10; python_version >= "3.6" and extra == "runtime-strict"
Requires-Dist: rich==12.3.0; extra == "runtime-strict"
Requires-Dist: git-python==1.0.0; python_version >= "2.7" and extra == "runtime-strict"
Requires-Dist: black==22.1.0; python_version >= "3.6.2" and extra == "runtime-strict"
Requires-Dist: packaging==21.3; extra == "runtime-strict"
Requires-Dist: ruamel.yaml<=0.17.32,==0.17.22; extra == "runtime-strict"
Requires-Dist: PyYAML==6.0.2; (python_version < "4.0" and python_version >= "3.12") and extra == "runtime-strict"
Requires-Dist: PyYAML==6.0; python_version < "3.12" and extra == "runtime-strict"
Requires-Dist: argcomplete==1.0; extra == "runtime-strict"
Requires-Dist: pandas==2.2.3; (python_version < "4.0" and python_version >= "3.13") and extra == "runtime-strict"
Requires-Dist: pandas==1.5.0; (python_version < "3.12" and python_version >= "3.11") and extra == "runtime-strict"
Requires-Dist: pandas==1.3.5; (python_version < "3.11" and python_version >= "3.10") and extra == "runtime-strict"
Requires-Dist: pandas==1.4.0; (python_version < "3.10" and python_version >= "3.9") and extra == "runtime-strict"
Requires-Dist: pandas==1.4.0; (python_version < "3.9" and python_version >= "3.8") and extra == "runtime-strict"
Requires-Dist: pandas==1.2.0; (python_version < "3.8" and python_version >= "3.7") and extra == "runtime-strict"
Requires-Dist: pandas==1.1.4; (python_version < "3.7" and python_version >= "3.6") and extra == "runtime-strict"
Requires-Dist: numpy==2.1.2; (python_version < "4.0" and python_version >= "3.13") and extra == "runtime-strict"
Requires-Dist: numpy==1.26.0; (python_version < "3.13" and python_version >= "3.12") and extra == "runtime-strict"
Requires-Dist: numpy==1.23.2; (python_version < "3.12" and python_version >= "3.11") and extra == "runtime-strict"
Requires-Dist: numpy==1.21.6; (python_version < "3.11" and python_version >= "3.10") and extra == "runtime-strict"
Requires-Dist: numpy==1.19.3; (python_version < "3.10" and python_version >= "3.9") and extra == "runtime-strict"
Requires-Dist: numpy==1.22.0; (sys_platform == "darwin" and python_version < "3.9" and python_version >= "3.8") and extra == "runtime-strict"
Requires-Dist: numpy==1.20.0; (sys_platform != "darwin" and python_version < "3.9" and python_version >= "3.8") and extra == "runtime-strict"
Requires-Dist: numpy==1.19.3; (python_version < "3.8" and python_version >= "3.7") and extra == "runtime-strict"
Requires-Dist: cmd_queue==0.1.6; extra == "runtime-strict"
Requires-Dist: sphinx==5.0.1; extra == "runtime-strict"
Requires-Dist: sphinx-autobuild==2021.3.14; extra == "runtime-strict"
Requires-Dist: sphinx_rtd_theme==1.0.0; extra == "runtime-strict"
Requires-Dist: sphinxcontrib-napoleon==0.7; extra == "runtime-strict"
Requires-Dist: sphinx-autoapi==1.8.4; extra == "runtime-strict"
Requires-Dist: Pygments==2.12.0; extra == "runtime-strict"
Requires-Dist: myst_parser==0.18.0; extra == "runtime-strict"
Requires-Dist: sphinx-reredirects==0.0.1; extra == "runtime-strict"
Requires-Dist: tabulate==0.9.0; extra == "runtime-strict"
Provides-Extra: tests-strict
Requires-Dist: xdoctest==1.1.6; extra == "tests-strict"
Requires-Dist: pytest==6.2.5; python_version >= "3.10.0" and extra == "tests-strict"
Requires-Dist: pytest==6.2.5; (python_version < "3.10.0" and python_version >= "3.7.0") and extra == "tests-strict"
Requires-Dist: pytest-cov==3.0.0; python_version >= "3.6.0" and extra == "tests-strict"
Requires-Dist: pytest-cov==2.9.0; (python_version < "3.6.0" and python_version >= "3.5.0") and extra == "tests-strict"
Requires-Dist: pytest-cov==2.8.1; (python_version < "3.5.0" and python_version >= "3.4.0") and extra == "tests-strict"
Requires-Dist: pytest-cov==2.8.1; (python_version < "2.8.0" and python_version >= "2.7.0") and extra == "tests-strict"
Requires-Dist: pytest-timeout==1.4.2; extra == "tests-strict"
Requires-Dist: coverage==6.1.1; python_version >= "3.10" and extra == "tests-strict"
Requires-Dist: coverage==5.3.1; (python_version < "3.10" and python_version >= "3.9") and extra == "tests-strict"
Requires-Dist: coverage==6.1.1; (python_version < "3.9" and python_version >= "3.8") and extra == "tests-strict"
Requires-Dist: coverage==6.1.1; (python_version < "3.8" and python_version >= "3.7") and extra == "tests-strict"
Requires-Dist: coverage==6.1.1; (python_version < "3.7" and python_version >= "3.6") and extra == "tests-strict"
Requires-Dist: coverage==5.3.1; (python_version < "3.6" and python_version >= "3.5") and extra == "tests-strict"
Requires-Dist: coverage==4.3.4; (python_version < "3.5" and python_version >= "3.4") and extra == "tests-strict"
Requires-Dist: coverage==5.3.1; (python_version < "3.4" and python_version >= "2.7") and extra == "tests-strict"
Requires-Dist: coverage==4.5; (python_version < "2.7" and python_version >= "2.6") and extra == "tests-strict"
Provides-Extra: optional-strict
Requires-Dist: python-gitlab==3.0; extra == "optional-strict"
Provides-Extra: docs-strict
Requires-Dist: sphinx==5.0.1; extra == "docs-strict"
Requires-Dist: sphinx-autobuild==2021.3.14; extra == "docs-strict"
Requires-Dist: sphinx_rtd_theme==1.0.0; extra == "docs-strict"
Requires-Dist: sphinxcontrib-napoleon==0.7; extra == "docs-strict"
Requires-Dist: sphinx-autoapi==1.8.4; extra == "docs-strict"
Requires-Dist: Pygments==2.9.0; extra == "docs-strict"
Requires-Dist: myst_parser==0.18.0; extra == "docs-strict"
Requires-Dist: sphinx-reredirects==0.0.1; extra == "docs-strict"
Requires-Dist: docutils==0.20.1; extra == "docs-strict"
Provides-Extra: gdal-strict-strict
Requires-Dist: GDAL==3.5.2; (python_version < "4.0" and python_version >= "3.11") and extra == "gdal-strict-strict"
Requires-Dist: GDAL==3.4.1; (python_version < "3.11" and python_version >= "3.10") and extra == "gdal-strict-strict"
Requires-Dist: GDAL==3.4.1; python_version <= "3.9" and extra == "gdal-strict-strict"
Provides-Extra: graphics-strict
Requires-Dist: opencv-python==4.5.5.64; (python_version < "4.0" and python_version >= "3.11") and extra == "graphics-strict"
Requires-Dist: opencv-python==4.5.4.58; (python_version < "3.11" and python_version >= "3.10") and extra == "graphics-strict"
Requires-Dist: opencv-python==3.4.15.55; (python_version < "3.10" and python_version >= "3.9") and extra == "graphics-strict"
Requires-Dist: opencv-python==3.4.15.55; (python_version < "3.9" and python_version >= "3.8") and extra == "graphics-strict"
Requires-Dist: opencv-python==3.4.15.55; (python_version < "3.8" and python_version >= "3.7") and extra == "graphics-strict"
Requires-Dist: opencv-python==3.4.13.47; (python_version < "3.7" and python_version >= "3.6") and extra == "graphics-strict"
Requires-Dist: opencv-python==3.1.0.2; (python_version < "3.6" and python_version >= "3.5") and extra == "graphics-strict"
Requires-Dist: opencv-python==3.1.0.5; (python_version < "3.5" and python_version >= "3.4") and extra == "graphics-strict"
Requires-Dist: opencv-python==3.1.0.0; (python_version < "3.4" and python_version >= "2.7") and extra == "graphics-strict"
Provides-Extra: headless-strict
Requires-Dist: opencv-python-headless==4.5.5.64; (python_version < "4.0" and python_version >= "3.11") and extra == "headless-strict"
Requires-Dist: opencv-python-headless==4.5.4.58; (python_version < "3.11" and python_version >= "3.10") and extra == "headless-strict"
Requires-Dist: opencv-python-headless==3.4.15.55; (python_version < "3.10" and python_version >= "3.9") and extra == "headless-strict"
Requires-Dist: opencv-python-headless==3.4.15.55; (python_version < "3.9" and python_version >= "3.8") and extra == "headless-strict"
Requires-Dist: opencv-python-headless==3.4.15.55; (python_version < "3.8" and python_version >= "3.7") and extra == "headless-strict"
Requires-Dist: opencv-python-headless==3.4.13.47; (python_version < "3.7" and python_version >= "3.6") and extra == "headless-strict"
Requires-Dist: opencv-python-headless==3.4.2.16; (python_version < "3.6" and python_version >= "3.5") and extra == "headless-strict"
Requires-Dist: opencv-python-headless==3.4.2.16; (python_version < "3.5" and python_version >= "3.4") and extra == "headless-strict"
Requires-Dist: opencv-python-headless==3.4.2.16; (python_version < "3.4" and python_version >= "2.7") and extra == "headless-strict"
Provides-Extra: postgresql-strict
Requires-Dist: psycopg2-binary==2.9.5; (python_version < "4.0" and python_version >= "3.11") and extra == "postgresql-strict"
Requires-Dist: psycopg2-binary==2.9.1; (python_version < "3.11" and python_version >= "3.10") and extra == "postgresql-strict"
Requires-Dist: psycopg2-binary==2.8.6; (python_version < "3.10" and python_version >= "3.9") and extra == "postgresql-strict"
Requires-Dist: psycopg2-binary==2.8.4; (python_version < "3.9" and python_version >= "3.8") and extra == "postgresql-strict"
Requires-Dist: psycopg2-binary==2.7.5; (python_version < "3.8" and python_version >= "3.7") and extra == "postgresql-strict"
Requires-Dist: psycopg2-binary==2.7.3.2; (python_version < "3.7" and python_version >= "3.6") and extra == "postgresql-strict"
Requires-Dist: sqlalchemy_utils==0.40.0; extra == "postgresql-strict"
Dynamic: author
Dynamic: author-email
Dynamic: classifier
Dynamic: description
Dynamic: description-content-type
Dynamic: home-page
Dynamic: license
Dynamic: license-file
Dynamic: provides-extra
Dynamic: requires-dist
Dynamic: requires-python
Dynamic: summary
